devgagantools/__init__.py
devgagantools/spylib.py
devgagantools-4.0.1.dist-info/LICENSE
devgagantools-4.0.1.dist-info/METADATA
devgagantools-4.0.1.dist-info/WHEEL
devgagantools-4.0.1.dist-info/top_level.txt
devgagantools-4.0.1.dist-info/RECORD
