Metadata-Version: 2.1
Name: devgagantools
Version: 4.0.1
Summary: This repository aimed to be fast uploading and fast downloading via Telethon (user and bots both supported)
Home-page: https://github.com/devgaganin/devgagantools
Author: devgagan
Author-email: business@devgagan.in
License: MIT
Classifier: License :: OSI Approved :: MIT License
Classifier: Programming Language :: Python :: 3.6
Classifier: Programming Language :: Python :: 3.7
Classifier: Programming Language :: Python :: 3.8
Classifier: Programming Language :: Python :: 3.9
Classifier: Operating System :: OS Independent
License-File: LICENSE
Requires-Dist: telethon
Requires-Dist: telethon-tgcrypto
Requires-Dist: aiofiles
